i050_utility_package-0.1.1.dist-info/licenses/LICENSE
i050utility/__init__.py
i050utility/cleaner.py
i050_utility_package-0.1.1.dist-info/METADATA
i050_utility_package-0.1.1.dist-info/WHEEL
i050_utility_package-0.1.1.dist-info/top_level.txt
i050_utility_package-0.1.1.dist-info/RECORD
