Metadata-Version: 2.4
Name: i050-utility-package
Version: 0.1.1
Summary: A utility for fast data sanitization and cleansing focusing on Pandas DataFrames.
Author-email: Your Name <your.email@example.com>
License: MIT
Classifier: Programming Language :: Python :: 3
Classifier: Programming Language :: Python :: 3.10
Classifier: License :: OSI Approved :: MIT License
Classifier: Topic :: Scientific/Engineering :: Information Analysis
Classifier: Development Status :: 3 - Alpha
Requires-Python: >=3.8
License-File: LICENSE
Requires-Dist: pandas>=1.0.0
Dynamic: license-file
